tests
yatcobot
