Metadata-Version: 1.1
Name: Yatcobot
Version: 2.3.3
Summary: The best bot for searching twitter contests and automatically retweet them
Home-page: https://github.com/buluba89/Yatcobot
Author: John Buluba
Author-email: UNKNOWN
License: UNKNOWN
Project-URL: Source, https://github.com/buluba89/Yatcobot
Keywords: twitter bot contest retweet
Platform: UNKNOWN
Classifier: License :: OSI Approved :: GNU General Public License v2 (GPLv2)
Classifier: Programming Language :: Python :: 3.4
Classifier: Programming Language :: Python :: 3.5
Classifier: Programming Language :: Python :: 3.6
